README.md
setup.py
compiler/__init__.py
compiler/__main__.py
compiler/config.py
compiler/consts.py
compiler/future.py
compiler/misc.py
compiler/pyassem.py
compiler/pycodegen.py
compiler/symbols.py
compiler/visitor.py
python_compiler.egg-info/PKG-INFO
python_compiler.egg-info/SOURCES.txt
python_compiler.egg-info/dependency_links.txt
python_compiler.egg-info/top_level.txt