Metadata-Version: 2.1
Name: python-compiler
Version: 1.1
Summary: Python bytecode compiler written in Python
Home-page: https://github.com/pfalcon/python-compiler
Author: Python Developers
Maintainer: Paul Sokolovsky
Maintainer-email: pfalcon@users.sourceforge.net
License: Python
Platform: UNKNOWN
